NucleoATAC-0.3.4.data/scripts/nucleoatac
NucleoATAC-0.3.4.data/scripts/pyatac
NucleoATAC-0.3.4.dist-info/DESCRIPTION.rst
NucleoATAC-0.3.4.dist-info/METADATA
NucleoATAC-0.3.4.dist-info/RECORD
NucleoATAC-0.3.4.dist-info/WHEEL
NucleoATAC-0.3.4.dist-info/metadata.json
NucleoATAC-0.3.4.dist-info/top_level.txt
nucleoatac/Magic.py
nucleoatac/NFRCalling.py
nucleoatac/NucleosomeCalling.py
nucleoatac/Occupancy.py
nucleoatac/__init__.py
nucleoatac/cli.py
nucleoatac/diff_occ.py
nucleoatac/merge.py
nucleoatac/multinomial_cov.pyx
nucleoatac/run_nfr.py
nucleoatac/run_nuc.py
nucleoatac/run_occ.py
nucleoatac/run_vprocess.py
nucleoatac/vplot/__init__.py
nucleoatac/vplot/standard_vplot.VMat
pyatac/Magic.py
pyatac/VMat.py
pyatac/__init__.py
pyatac/bedgraph.py
pyatac/bias.py
pyatac/chunk.py
pyatac/chunkmat2d.py
pyatac/cli.py
pyatac/fragments.pyx
pyatac/fragments.pyxbld
pyatac/fragments.pyxbldc
pyatac/fragmentsizes.py
pyatac/get_counts.py
pyatac/get_cov.py
pyatac/get_ins.py
pyatac/get_nucleotide.py
pyatac/get_pwm.py
pyatac/get_sizes.py
pyatac/make_bias_track.py
pyatac/make_bias_vplot.py
pyatac/make_vplot.py
pyatac/seq.py
pyatac/signal_around_sites.py
pyatac/tracks.py
pyatac/utils.py
pyatac/pwm/Human.PWM.txt
pyatac/pwm/Human2.PWM.txt
pyatac/pwm/Yeast.PWM.txt
pyatac/pwm/__init__.py
